stonefish_si/__init__.py
stonefish_si/_fingerprint.py
stonefish_si/_ip.py
stonefish_si-0.1.1.dist-info/METADATA
stonefish_si-0.1.1.dist-info/WHEEL
stonefish_si-0.1.1.dist-info/top_level.txt
stonefish_si-0.1.1.dist-info/RECORD
