Metadata-Version: 2.4
Name: stonefish-si
Version: 0.1.1
Summary: Stonefish helper package
Author-email: Nico Schlömer <nico.schloemer@gmail.com>
Classifier: Development Status :: 4 - Beta
Classifier: License :: Other/Proprietary License
Classifier: Operating System :: OS Independent
Classifier: Programming Language :: Python
Classifier: Programming Language :: Python :: 3 :: Only
Classifier: Programming Language :: Python :: 3.9
Classifier: Programming Language :: Python :: 3.10
Classifier: Programming Language :: Python :: 3.11
Classifier: Programming Language :: Python :: 3.12
Classifier: Programming Language :: Python :: 3.13
Classifier: Topic :: Utilities
Requires-Python: >=3.9
Requires-Dist: getmac
Requires-Dist: py-machineid
Requires-Dist: requests
Requires-Dist: x22>=0.2.1
